{
  "eventId": "minx",
  "competitionId": "BruggeBeginnersOpen2024",
  "rounds": {
    "c": [
      {
        "scrambleNum": "1",
        "scramble": "R++ D++ R++ D++ R-- D++ R-- D-- R-- D++ U\\nR-- D++ R++ D-- R-- D-- R-- D++ R++ D++ U\\nR++ D-- R-- D++ R-- D-- R-- D++ R++ D++ U\\nR++ D++ R-- D++ R++ D-- R-- D++ R-- D-- U'\\nR-- D++ R-- D++ R++ D-- R-- D++ R++ D++ U\\nR-- D++ R++ D++ R++ D-- R++ D++ R-- D-- U'\\nR++ D-- R-- D-- R++ D-- R++ D++ R-- D++ U",
        "scrambleId": 3620921,
        "isExtra": 0,
        "groupId": "A"
      },
      {
        "scrambleNum": "2",
        "scramble": "R-- D-- R++ D++ R++ D-- R-- D-- R-- D-- U'\\nR-- D++ R++ D-- R++ D-- R-- D-- R-- D-- U'\\nR++ D++ R++ D++ R++ D-- R-- D++ R++ D++ U\\nR++ D++ R++ D-- R++ D++ R++ D-- R-- D++ U\\nR-- D++ R-- D++ R++ D++ R-- D-- R-- D-- U'\\nR-- D++ R++ D-- R++ D++ R++ D++ R++ D++ U\\nR++ D++ R-- D-- R++ D-- R-- D++ R++ D-- U'",
        "scrambleId": 3620922,
        "isExtra": 0,
        "groupId": "A"
      },
      {
        "scrambleNum": "3",
        "scramble": "R-- D++ R++ D-- R-- D++ R-- D++ R++ D-- U'\\nR-- D-- R-- D-- R-- D-- R-- D++ R-- D-- U'\\nR-- D++ R-- D++ R-- D++ R-- D++ R++ D++ U\\nR-- D-- R-- D++ R++ D++ R++ D-- R-- D-- U'\\nR-- D-- R-- D-- R-- D++ R-- D++ R-- D-- U'\\nR-- D++ R-- D++ R-- D-- R-- D++ R++ D++ U\\nR-- D++ R-- D-- R-- D-- R-- D-- R-- D-- U'",
        "scrambleId": 3620923,
        "isExtra": 0,
        "groupId": "A"
      },
      {
        "scrambleNum": "4",
        "scramble": "R-- D++ R-- D-- R-- D++ R-- D-- R-- D++ U\\nR++ D++ R-- D-- R-- D-- R++ D++ R-- D++ U\\nR++ D++ R++ D++ R++ D-- R++ D++ R++ D-- U'\\nR-- D-- R++ D-- R++ D-- R-- D-- R-- D-- U'\\nR-- D-- R-- D-- R++ D++ R++ D++ R-- D++ U\\nR-- D++ R-- D++ R-- D++ R-- D-- R++ D-- U'\\nR++ D-- R++ D-- R++ D++ R++ D-- R++ D-- U'",
        "scrambleId": 3620924,
        "isExtra": 0,
        "groupId": "A"
      },
      {
        "scrambleNum": "5",
        "scramble": "R-- D++ R++ D-- R-- D-- R++ D-- R++ D-- U'\\nR++ D-- R-- D-- R-- D-- R++ D++ R++ D++ U\\nR-- D-- R-- D-- R++ D-- R-- D++ R-- D-- U'\\nR++ D++ R++ D++ R-- D++ R-- D-- R-- D++ U\\nR-- D-- R++ D++ R++ D-- R-- D++ R++ D-- U'\\nR-- D-- R++ D-- R-- D-- R++ D++ R-- D-- U'\\nR-- D-- R-- D-- R-- D-- R-- D-- R++ D++ U",
        "scrambleId": 3620925,
        "isExtra": 0,
        "groupId": "A"
      },
      {
        "scrambleNum": "1",
        "scramble": "R-- D-- R-- D-- R-- D-- R++ D++ R++ D-- U'\\nR++ D++ R++ D-- R++ D-- R-- D++ R-- D++ U\\nR++ D-- R++ D++ R++ D++ R-- D++ R-- D-- U'\\nR++ D++ R-- D++ R-- D-- R++ D++ R-- D++ U\\nR-- D++ R++ D++ R-- D++ R-- D++ R-- D++ U\\nR++ D-- R-- D++ R-- D++ R-- D++ R++ D++ U\\nR++ D++ R++ D++ R++ D++ R-- D++ R-- D-- U'",
        "scrambleId": 3620926,
        "isExtra": 1,
        "groupId": "A"
      },
      {
        "scrambleNum": "2",
        "scramble": "R-- D-- R-- D-- R-- D++ R-- D-- R-- D++ U\\nR-- D++ R++ D-- R++ D-- R++ D++ R++ D-- U'\\nR++ D-- R++ D-- R-- D-- R-- D++ R-- D-- U'\\nR++ D++ R-- D++ R++ D++ R++ D-- R-- D-- U'\\nR-- D++ R-- D++ R++ D-- R++ D++ R-- D++ U\\nR++ D++ R-- D-- R-- D-- R-- D-- R++ D++ U\\nR++ D-- R-- D-- R-- D++ R-- D++ R++ D++ U",
        "scrambleId": 3620927,
        "isExtra": 1,
        "groupId": "A"
      },
      {
        "scrambleNum": "1",
        "scramble": "R++ D++ R-- D++ R-- D-- R++ D++ R++ D-- U'\\nR++ D++ R++ D-- R++ D-- R++ D++ R++ D++ U\\nR++ D-- R++ D-- R-- D-- R-- D++ R++ D-- U'\\nR-- D++ R++ D++ R++ D-- R++ D++ R-- D++ U\\nR++ D++ R++ D-- R++ D-- R++ D-- R-- D-- U'\\nR++ D-- R++ D++ R-- D++ R++ D++ R-- D++ U\\nR-- D-- R++ D-- R++ D-- R++ D-- R++ D++ U",
        "scrambleId": 3620928,
        "isExtra": 0,
        "groupId": "B"
      },
      {
        "scrambleNum": "2",
        "scramble": "R++ D-- R++ D++ R++ D-- R-- D-- R-- D-- U'\\nR-- D++ R-- D++ R++ D++ R++ D-- R++ D++ U\\nR++ D++ R-- D-- R-- D-- R-- D++ R-- D-- U'\\nR-- D-- R++ D-- R-- D++ R-- D++ R-- D++ U\\nR-- D++ R-- D++ R++ D++ R++ D++ R++ D++ U\\nR-- D++ R++ D-- R-- D++ R-- D-- R-- D-- U'\\nR++ D++ R-- D-- R++ D-- R-- D-- R++ D++ U",
        "scrambleId": 3620929,
        "isExtra": 0,
        "groupId": "B"
      },
      {
        "scrambleNum": "3",
        "scramble": "R++ D++ R++ D++ R-- D++ R-- D++ R++ D++ U\\nR-- D-- R++ D++ R-- D++ R++ D-- R-- D-- U'\\nR++ D++ R-- D-- R++ D-- R++ D++ R-- D++ U\\nR++ D-- R++ D-- R-- D++ R-- D-- R-- D-- U'\\nR++ D++ R-- D-- R++ D-- R++ D++ R-- D++ U\\nR-- D-- R-- D++ R++ D++ R++ D-- R++ D++ U\\nR-- D++ R++ D-- R++ D-- R++ D++ R-- D-- U'",
        "scrambleId": 3620930,
        "isExtra": 0,
        "groupId": "B"
      },
      {
        "scrambleNum": "4",
        "scramble": "R++ D-- R-- D++ R-- D++ R-- D-- R++ D-- U'\\nR++ D-- R-- D-- R-- D++ R-- D++ R-- D++ U\\nR-- D++ R-- D++ R-- D++ R++ D-- R++ D++ U\\nR++ D++ R-- D++ R-- D-- R++ D++ R++ D++ U\\nR-- D++ R++ D-- R-- D-- R-- D++ R-- D++ U\\nR-- D-- R++ D-- R++ D++ R-- D++ R++ D++ U\\nR-- D++ R-- D++ R++ D-- R-- D-- R++ D-- U'",
        "scrambleId": 3620931,
        "isExtra": 0,
        "groupId": "B"
      },
      {
        "scrambleNum": "5",
        "scramble": "R-- D-- R++ D-- R++ D++ R++ D-- R++ D-- U'\\nR-- D-- R-- D++ R-- D-- R-- D-- R-- D-- U'\\nR++ D++ R-- D-- R-- D-- R-- D++ R-- D++ U\\nR++ D++ R-- D-- R-- D++ R++ D++ R++ D-- U'\\nR++ D++ R++ D++ R++ D-- R-- D++ R++ D-- U'\\nR++ D-- R++ D++ R++ D-- R++ D-- R++ D-- U'\\nR-- D++ R-- D-- R++ D-- R++ D-- R++ D-- U'",
        "scrambleId": 3620932,
        "isExtra": 0,
        "groupId": "B"
      },
      {
        "scrambleNum": "1",
        "scramble": "R++ D-- R++ D++ R++ D++ R++ D-- R-- D++ U\\nR-- D-- R++ D-- R-- D-- R-- D++ R-- D-- U'\\nR++ D-- R++ D-- R++ D-- R++ D-- R++ D-- U'\\nR++ D++ R++ D++ R-- D-- R-- D++ R-- D-- U'\\nR++ D++ R++ D++ R++ D++ R-- D-- R-- D-- U'\\nR-- D++ R++ D-- R++ D++ R-- D-- R++ D++ U\\nR++ D++ R-- D-- R++ D++ R++ D++ R++ D-- U'",
        "scrambleId": 3620933,
        "isExtra": 1,
        "groupId": "B"
      },
      {
        "scrambleNum": "2",
        "scramble": "R++ D-- R++ D-- R-- D-- R++ D-- R++ D++ U\\nR++ D-- R++ D-- R++ D-- R-- D-- R++ D++ U\\nR++ D++ R++ D++ R++ D++ R++ D-- R-- D-- U'\\nR++ D++ R++ D++ R-- D-- R-- D-- R-- D-- U'\\nR-- D++ R++ D++ R++ D++ R++ D++ R-- D-- U'\\nR++ D++ R++ D-- R-- D-- R-- D++ R++ D-- U'\\nR-- D++ R++ D-- R-- D-- R-- D++ R++ D++ U",
        "scrambleId": 3620934,
        "isExtra": 1,
        "groupId": "B"
      }
    ]
  }
}