{
  "eventId": "skewb",
  "competitionId": "Hike2CubeKenya2023",
  "rounds": {
    "f": [
      {
        "scrambleNum": "1",
        "scramble": "L R' B L' B' L R L' R L U",
        "scrambleId": 3306233,
        "isExtra": 0,
        "groupId": "A"
      },
      {
        "scrambleNum": "2",
        "scramble": "R U R' L U' L' U' B' R' U R'",
        "scrambleId": 3306234,
        "isExtra": 0,
        "groupId": "A"
      },
      {
        "scrambleNum": "3",
        "scramble": "R L R B R' B L' U B' U B",
        "scrambleId": 3306235,
        "isExtra": 0,
        "groupId": "A"
      },
      {
        "scrambleNum": "4",
        "scramble": "U B U' R' U R' L U B' U' R",
        "scrambleId": 3306236,
        "isExtra": 0,
        "groupId": "A"
      },
      {
        "scrambleNum": "5",
        "scramble": "L R B R' B U' L' U' R' U R",
        "scrambleId": 3306237,
        "isExtra": 0,
        "groupId": "A"
      },
      {
        "scrambleNum": "1",
        "scramble": "B R B R L B' U' R U L B'",
        "scrambleId": 3306238,
        "isExtra": 1,
        "groupId": "A"
      },
      {
        "scrambleNum": "2",
        "scramble": "R U L' R' L' R' B U' L U' L",
        "scrambleId": 3306239,
        "isExtra": 1,
        "groupId": "A"
      }
    ]
  }
}