{
  "eventId": "skewb",
  "competitionId": "MathsocDelhiOpen2024",
  "rounds": {
    "d": [
      {
        "scrambleNum": "1",
        "scramble": "U B' R' U B U R' U R' U' B",
        "scrambleId": "3491519",
        "isExtra": 0,
        "groupId": "A"
      },
      {
        "scrambleNum": "2",
        "scramble": "R L U' B L R B L' B L B'",
        "scrambleId": "3491520",
        "isExtra": 0,
        "groupId": "A"
      },
      {
        "scrambleNum": "3",
        "scramble": "L R U L' B' L' B' U' B' L B'",
        "scrambleId": "3491521",
        "isExtra": 0,
        "groupId": "A"
      },
      {
        "scrambleNum": "4",
        "scramble": "B L U' R U R B U' R L R",
        "scrambleId": "3491522",
        "isExtra": 0,
        "groupId": "A"
      },
      {
        "scrambleNum": "5",
        "scramble": "R U B U R L B' L' U' R B",
        "scrambleId": "3491523",
        "isExtra": 0,
        "groupId": "A"
      },
      {
        "scrambleNum": "1",
        "scramble": "B R U' L' U B' R L' R' U B",
        "scrambleId": "3491524",
        "isExtra": 1,
        "groupId": "A"
      },
      {
        "scrambleNum": "2",
        "scramble": "U R U R' U R' L R' B' R L'",
        "scrambleId": "3491525",
        "isExtra": 1,
        "groupId": "A"
      },
      {
        "scrambleNum": "1",
        "scramble": "R B R U L' B L' U L' U' L'",
        "scrambleId": "3491526",
        "isExtra": 0,
        "groupId": "B"
      },
      {
        "scrambleNum": "2",
        "scramble": "R U L R U R' U L' R' B L",
        "scrambleId": "3491527",
        "isExtra": 0,
        "groupId": "B"
      },
      {
        "scrambleNum": "3",
        "scramble": "R U R U B L U' R B' U R'",
        "scrambleId": "3491528",
        "isExtra": 0,
        "groupId": "B"
      },
      {
        "scrambleNum": "4",
        "scramble": "L R B' R U R' L' R L R L'",
        "scrambleId": "3491529",
        "isExtra": 0,
        "groupId": "B"
      },
      {
        "scrambleNum": "5",
        "scramble": "U B' U' B R' U' B' U L' B' U",
        "scrambleId": "3491530",
        "isExtra": 0,
        "groupId": "B"
      },
      {
        "scrambleNum": "1",
        "scramble": "U L U' L' R B' L' U L R' B'",
        "scrambleId": "3491531",
        "isExtra": 1,
        "groupId": "B"
      },
      {
        "scrambleNum": "2",
        "scramble": "B U R' L R L' R' B L' U' B'",
        "scrambleId": "3491532",
        "isExtra": 1,
        "groupId": "B"
      },
      {
        "scrambleNum": "1",
        "scramble": "L R L B' R L U' R' U B U'",
        "scrambleId": "3491533",
        "isExtra": 0,
        "groupId": "C"
      },
      {
        "scrambleNum": "2",
        "scramble": "L R' L R U' L' B' U' L' U' R'",
        "scrambleId": "3491534",
        "isExtra": 0,
        "groupId": "C"
      },
      {
        "scrambleNum": "3",
        "scramble": "R U R B R U' L R L' U R'",
        "scrambleId": "3491535",
        "isExtra": 0,
        "groupId": "C"
      },
      {
        "scrambleNum": "4",
        "scramble": "L R L' U B U B' R' U' L R'",
        "scrambleId": "3491536",
        "isExtra": 0,
        "groupId": "C"
      },
      {
        "scrambleNum": "5",
        "scramble": "R B U B L U' R' L U R L",
        "scrambleId": "3491537",
        "isExtra": 0,
        "groupId": "C"
      },
      {
        "scrambleNum": "1",
        "scramble": "U B U R' L' R U' R' B L' B",
        "scrambleId": "3491538",
        "isExtra": 1,
        "groupId": "C"
      },
      {
        "scrambleNum": "2",
        "scramble": "L R' L R L' R U' R B' R' B",
        "scrambleId": "3491539",
        "isExtra": 1,
        "groupId": "C"
      },
      {
        "scrambleNum": "1",
        "scramble": "B L B' L R L' B' U' B U' L",
        "scrambleId": "3491540",
        "isExtra": 0,
        "groupId": "D"
      },
      {
        "scrambleNum": "2",
        "scramble": "U L U R' B' R B L' U' R L",
        "scrambleId": "3491541",
        "isExtra": 0,
        "groupId": "D"
      },
      {
        "scrambleNum": "3",
        "scramble": "L R B L' R B' U' B R' L' R",
        "scrambleId": "3491542",
        "isExtra": 0,
        "groupId": "D"
      },
      {
        "scrambleNum": "4",
        "scramble": "B R U' B' L' B R' L' B' U R'",
        "scrambleId": "3491543",
        "isExtra": 0,
        "groupId": "D"
      },
      {
        "scrambleNum": "5",
        "scramble": "L R U' R' U' R B' U L R' U'",
        "scrambleId": "3491544",
        "isExtra": 0,
        "groupId": "D"
      },
      {
        "scrambleNum": "1",
        "scramble": "U L R' L' B U B L R U B",
        "scrambleId": "3491545",
        "isExtra": 1,
        "groupId": "D"
      },
      {
        "scrambleNum": "2",
        "scramble": "B L R' U' L' U L' B L' B U'",
        "scrambleId": "3491546",
        "isExtra": 1,
        "groupId": "D"
      },
      {
        "scrambleNum": "1",
        "scramble": "R U B' L' U B U L R' U' B",
        "scrambleId": "3491547",
        "isExtra": 0,
        "groupId": "E"
      },
      {
        "scrambleNum": "2",
        "scramble": "B R U' L R' B' L R L B R",
        "scrambleId": "3491548",
        "isExtra": 0,
        "groupId": "E"
      },
      {
        "scrambleNum": "3",
        "scramble": "U B L R U' L' B L' U B U",
        "scrambleId": "3491549",
        "isExtra": 0,
        "groupId": "E"
      },
      {
        "scrambleNum": "4",
        "scramble": "L R U L U' L U' B' R L R",
        "scrambleId": "3491550",
        "isExtra": 0,
        "groupId": "E"
      },
      {
        "scrambleNum": "5",
        "scramble": "L B U R' B L' U L' R U' B'",
        "scrambleId": "3491551",
        "isExtra": 0,
        "groupId": "E"
      },
      {
        "scrambleNum": "1",
        "scramble": "U L' R' B R L U' R L B' R",
        "scrambleId": "3491552",
        "isExtra": 1,
        "groupId": "E"
      },
      {
        "scrambleNum": "2",
        "scramble": "B L R B' L' R L' R B' L' R",
        "scrambleId": "3491553",
        "isExtra": 1,
        "groupId": "E"
      }
    ],
    "f": [
      {
        "scrambleNum": "1",
        "scramble": "B R B R L B' R U B' L' U",
        "scrambleId": "3491554",
        "isExtra": 0,
        "groupId": "A"
      },
      {
        "scrambleNum": "2",
        "scramble": "B R U R L B' L R B L U",
        "scrambleId": "3491555",
        "isExtra": 0,
        "groupId": "A"
      },
      {
        "scrambleNum": "3",
        "scramble": "R B U B' U R B L' R U' L'",
        "scrambleId": "3491556",
        "isExtra": 0,
        "groupId": "A"
      },
      {
        "scrambleNum": "4",
        "scramble": "B U B L U' B R' U' B U' L'",
        "scrambleId": "3491557",
        "isExtra": 0,
        "groupId": "A"
      },
      {
        "scrambleNum": "5",
        "scramble": "U L R' L U B' U' L' B U' R",
        "scrambleId": "3491558",
        "isExtra": 0,
        "groupId": "A"
      },
      {
        "scrambleNum": "1",
        "scramble": "R U R' L' B R' U B' L' R' L",
        "scrambleId": "3491559",
        "isExtra": 1,
        "groupId": "A"
      },
      {
        "scrambleNum": "2",
        "scramble": "B U B' L' R' L R' U' R' L' R",
        "scrambleId": "3491560",
        "isExtra": 1,
        "groupId": "A"
      }
    ]
  }
}