{
  "eventId": "skewb",
  "competitionId": "PrebleSpring2025",
  "rounds": {
    "1": [
      {
        "scrambleNum": "1",
        "scramble": "R B L R L' U R B' R L' U'",
        "scrambleId": 4637571,
        "isExtra": 0,
        "groupId": "A"
      },
      {
        "scrambleNum": "2",
        "scramble": "B L U R B' R' U L B U' L'",
        "scrambleId": 4637572,
        "isExtra": 0,
        "groupId": "A"
      },
      {
        "scrambleNum": "3",
        "scramble": "B U B U' R' U L' B' L' R' L",
        "scrambleId": 4637573,
        "isExtra": 0,
        "groupId": "A"
      },
      {
        "scrambleNum": "4",
        "scramble": "B U B R U B' L' U B L' R",
        "scrambleId": 4637574,
        "isExtra": 0,
        "groupId": "A"
      },
      {
        "scrambleNum": "5",
        "scramble": "L R B R L' B L B' R L B'",
        "scrambleId": 4637575,
        "isExtra": 0,
        "groupId": "A"
      },
      {
        "scrambleNum": "1",
        "scramble": "L U B' R B U B' L B L' U",
        "scrambleId": 4637576,
        "isExtra": 1,
        "groupId": "A"
      },
      {
        "scrambleNum": "2",
        "scramble": "U B L B R' L' R' B R' B' U",
        "scrambleId": 4637577,
        "isExtra": 1,
        "groupId": "A"
      },
      {
        "scrambleNum": "1",
        "scramble": "L R U R' L B R' L' R L' U",
        "scrambleId": 4637578,
        "isExtra": 0,
        "groupId": "B"
      },
      {
        "scrambleNum": "2",
        "scramble": "U B U L U R' L' B U' L R'",
        "scrambleId": 4637579,
        "isExtra": 0,
        "groupId": "B"
      },
      {
        "scrambleNum": "3",
        "scramble": "L R U' L' U' R' U' L' B R L",
        "scrambleId": 4637580,
        "isExtra": 0,
        "groupId": "B"
      },
      {
        "scrambleNum": "4",
        "scramble": "L B L' R' L U' L' U R B' R",
        "scrambleId": 4637581,
        "isExtra": 0,
        "groupId": "B"
      },
      {
        "scrambleNum": "5",
        "scramble": "R B L' U' B' R' L B R U L'",
        "scrambleId": 4637582,
        "isExtra": 0,
        "groupId": "B"
      },
      {
        "scrambleNum": "1",
        "scramble": "L R U R L B' L' B' U B' L",
        "scrambleId": 4637583,
        "isExtra": 1,
        "groupId": "B"
      },
      {
        "scrambleNum": "2",
        "scramble": "R U' B L' B' R B R B' R' U",
        "scrambleId": 4637584,
        "isExtra": 1,
        "groupId": "B"
      },
      {
        "scrambleNum": "1",
        "scramble": "U L U' B' U R' U B' R' U R",
        "scrambleId": 4637585,
        "isExtra": 0,
        "groupId": "C"
      },
      {
        "scrambleNum": "2",
        "scramble": "L U R' B U' R' L R' B' L' U",
        "scrambleId": 4637586,
        "isExtra": 0,
        "groupId": "C"
      },
      {
        "scrambleNum": "3",
        "scramble": "L B R' L' R' U' B' L' U' L' B",
        "scrambleId": 4637587,
        "isExtra": 0,
        "groupId": "C"
      },
      {
        "scrambleNum": "4",
        "scramble": "R B U' B' U' B' R L B R U'",
        "scrambleId": 4637588,
        "isExtra": 0,
        "groupId": "C"
      },
      {
        "scrambleNum": "5",
        "scramble": "B L' B R B L' R B' U B R",
        "scrambleId": 4637589,
        "isExtra": 0,
        "groupId": "C"
      },
      {
        "scrambleNum": "1",
        "scramble": "B L U L R B' U B' U' R' B",
        "scrambleId": 4637590,
        "isExtra": 1,
        "groupId": "C"
      },
      {
        "scrambleNum": "2",
        "scramble": "U R B' R L R' U B R' B R",
        "scrambleId": 4637591,
        "isExtra": 1,
        "groupId": "C"
      },
      {
        "scrambleNum": "1",
        "scramble": "U R B' R B' U' R' L' U R B'",
        "scrambleId": 4637592,
        "isExtra": 0,
        "groupId": "D"
      },
      {
        "scrambleNum": "2",
        "scramble": "U B L' B' L B' L U' B R' L",
        "scrambleId": 4637593,
        "isExtra": 0,
        "groupId": "D"
      },
      {
        "scrambleNum": "3",
        "scramble": "B U R U' B U R' B' U' R' L",
        "scrambleId": 4637594,
        "isExtra": 0,
        "groupId": "D"
      },
      {
        "scrambleNum": "4",
        "scramble": "R U L U' R' L U L' B' L R",
        "scrambleId": 4637595,
        "isExtra": 0,
        "groupId": "D"
      },
      {
        "scrambleNum": "5",
        "scramble": "R L U' L R' U B' R B' R U",
        "scrambleId": 4637596,
        "isExtra": 0,
        "groupId": "D"
      },
      {
        "scrambleNum": "1",
        "scramble": "R L B' R' B' L U' B' L' B' R'",
        "scrambleId": 4637597,
        "isExtra": 1,
        "groupId": "D"
      },
      {
        "scrambleNum": "2",
        "scramble": "L U L R' U L' R B R B' L",
        "scrambleId": 4637598,
        "isExtra": 1,
        "groupId": "D"
      }
    ],
    "f": [
      {
        "scrambleNum": "1",
        "scramble": "L U R' B' R B' U B U' L' R",
        "scrambleId": 4637599,
        "isExtra": 0,
        "groupId": "A"
      },
      {
        "scrambleNum": "2",
        "scramble": "L B R' L' B L' U' R L' B U'",
        "scrambleId": 4637600,
        "isExtra": 0,
        "groupId": "A"
      },
      {
        "scrambleNum": "3",
        "scramble": "R U' B R U' B R U' B U L'",
        "scrambleId": 4637601,
        "isExtra": 0,
        "groupId": "A"
      },
      {
        "scrambleNum": "4",
        "scramble": "R L B L B L' R L B' U R",
        "scrambleId": 4637602,
        "isExtra": 0,
        "groupId": "A"
      },
      {
        "scrambleNum": "5",
        "scramble": "R U B' U B L B U' B U' B",
        "scrambleId": 4637603,
        "isExtra": 0,
        "groupId": "A"
      },
      {
        "scrambleNum": "1",
        "scramble": "R B U L R' U B L U B' U'",
        "scrambleId": 4637604,
        "isExtra": 1,
        "groupId": "A"
      },
      {
        "scrambleNum": "2",
        "scramble": "U B L' U R' B' R U' B' U' B'",
        "scrambleId": 4637605,
        "isExtra": 1,
        "groupId": "A"
      }
    ]
  }
}