{
  "eventId": "pyram",
  "competitionId": "CubersEve2014",
  "rounds": {
    "d": [
      {
        "scrambleNum": "1",
        "scramble": "R U R B' U L B' R' L R L' u r'",
        "scrambleId": 93103,
        "isExtra": 0,
        "groupId": "A"
      },
      {
        "scrambleNum": "2",
        "scramble": "B' U' R B L' B' U B L B U l r'",
        "scrambleId": 93104,
        "isExtra": 0,
        "groupId": "A"
      },
      {
        "scrambleNum": "3",
        "scramble": "L U' L B' L' B' L' B U L' U l' b",
        "scrambleId": 93105,
        "isExtra": 0,
        "groupId": "A"
      },
      {
        "scrambleNum": "4",
        "scramble": "U L B L R' U B' R B' U L l' r b'",
        "scrambleId": 93106,
        "isExtra": 0,
        "groupId": "A"
      },
      {
        "scrambleNum": "5",
        "scramble": "L R' B U L R' U' L U' B' U' l' r b",
        "scrambleId": 93107,
        "isExtra": 0,
        "groupId": "A"
      },
      {
        "scrambleNum": "1",
        "scramble": "U' L U B R' U B L B' R' L' u' l' r b'",
        "scrambleId": 93108,
        "isExtra": 1,
        "groupId": "A"
      },
      {
        "scrambleNum": "2",
        "scramble": "B' U B' L' R L R L R' L' B' u r b",
        "scrambleId": 93109,
        "isExtra": 1,
        "groupId": "A"
      },
      {
        "scrambleNum": "1",
        "scramble": "U' L B R' U' B L R U' B' R u l",
        "scrambleId": 93110,
        "isExtra": 0,
        "groupId": "B"
      },
      {
        "scrambleNum": "2",
        "scramble": "R B' U L B R U' R' B' R U u' l r",
        "scrambleId": 93111,
        "isExtra": 0,
        "groupId": "B"
      },
      {
        "scrambleNum": "3",
        "scramble": "B R U' L R' U L' R U R B u' l' r'",
        "scrambleId": 93112,
        "isExtra": 0,
        "groupId": "B"
      },
      {
        "scrambleNum": "4",
        "scramble": "R L R' L U R B L R' U' B' u l' r",
        "scrambleId": 93113,
        "isExtra": 0,
        "groupId": "B"
      },
      {
        "scrambleNum": "5",
        "scramble": "B L R' L' B' R' U' B L U' B' l' r b'",
        "scrambleId": 93114,
        "isExtra": 0,
        "groupId": "B"
      },
      {
        "scrambleNum": "1",
        "scramble": "L R' U' B' U' L R' B L' B' R r b",
        "scrambleId": 93115,
        "isExtra": 1,
        "groupId": "B"
      },
      {
        "scrambleNum": "2",
        "scramble": "L U' L R' B' U' L' U' B' R' L l' r' b",
        "scrambleId": 93116,
        "isExtra": 1,
        "groupId": "B"
      }
    ],
    "f": [
      {
        "scrambleNum": "1",
        "scramble": "L R L' R L' B L' B U B' R' u r' b'",
        "scrambleId": 93117,
        "isExtra": 0,
        "groupId": "A"
      },
      {
        "scrambleNum": "2",
        "scramble": "U B' U B L R' U' B' U' B' L u b'",
        "scrambleId": 93118,
        "isExtra": 0,
        "groupId": "A"
      },
      {
        "scrambleNum": "3",
        "scramble": "B' L' U' B R B L' R U B' U' r",
        "scrambleId": 93119,
        "isExtra": 0,
        "groupId": "A"
      },
      {
        "scrambleNum": "4",
        "scramble": "R' L R' B U' B' U' B' R L' U' l' r b'",
        "scrambleId": 93120,
        "isExtra": 0,
        "groupId": "A"
      },
      {
        "scrambleNum": "5",
        "scramble": "R' U' R' U' L B' U' L' B' U R' u l' r b",
        "scrambleId": 93121,
        "isExtra": 0,
        "groupId": "A"
      },
      {
        "scrambleNum": "1",
        "scramble": "B U' L' U' B' L R B L U B u' l' r",
        "scrambleId": 93122,
        "isExtra": 1,
        "groupId": "A"
      },
      {
        "scrambleNum": "2",
        "scramble": "L B R U L B R' U B U B l b",
        "scrambleId": 93123,
        "isExtra": 1,
        "groupId": "A"
      }
    ]
  }
}