{
  "eventId": "pyram",
  "competitionId": "CubestuffCenturionQ12025",
  "rounds": {
    "d": [
      {
        "scrambleNum": "1",
        "scramble": "R' B R U' L' R U' L' R U B' u' r b'",
        "scrambleId": 4557400,
        "isExtra": 0,
        "groupId": "A"
      },
      {
        "scrambleNum": "2",
        "scramble": "R U' L U' L U L' R' L' R B' l",
        "scrambleId": 4557401,
        "isExtra": 0,
        "groupId": "A"
      },
      {
        "scrambleNum": "3",
        "scramble": "B' R' B' L' R' L' B U' B' R' L' l'",
        "scrambleId": 4557402,
        "isExtra": 0,
        "groupId": "A"
      },
      {
        "scrambleNum": "4",
        "scramble": "R U' B' L R' L R U L' R B l b'",
        "scrambleId": 4557403,
        "isExtra": 0,
        "groupId": "A"
      },
      {
        "scrambleNum": "5",
        "scramble": "R' U B R' L' U' R' B' L' R' B' u l' r' b",
        "scrambleId": 4557404,
        "isExtra": 0,
        "groupId": "A"
      },
      {
        "scrambleNum": "1",
        "scramble": "L' U L' B U R' U L B U B u l' b",
        "scrambleId": 4557405,
        "isExtra": 1,
        "groupId": "A"
      },
      {
        "scrambleNum": "2",
        "scramble": "U L' B' L' U' R' L' B U' B U u l r' b'",
        "scrambleId": 4557406,
        "isExtra": 1,
        "groupId": "A"
      },
      {
        "scrambleNum": "1",
        "scramble": "B L' B' L R' L R' B' R' L' U' u l r'",
        "scrambleId": 4557407,
        "isExtra": 0,
        "groupId": "B"
      },
      {
        "scrambleNum": "2",
        "scramble": "L R L' B' U L R B L U' B l b'",
        "scrambleId": 4557408,
        "isExtra": 0,
        "groupId": "B"
      },
      {
        "scrambleNum": "3",
        "scramble": "U' B R U B L U' L' U' B' L' u",
        "scrambleId": 4557409,
        "isExtra": 0,
        "groupId": "B"
      },
      {
        "scrambleNum": "4",
        "scramble": "U R' B' U R U' L R' B' R B' u b'",
        "scrambleId": 4557410,
        "isExtra": 0,
        "groupId": "B"
      },
      {
        "scrambleNum": "5",
        "scramble": "B R' U' B U B' L' R' L R B' u' r b",
        "scrambleId": 4557411,
        "isExtra": 0,
        "groupId": "B"
      },
      {
        "scrambleNum": "1",
        "scramble": "B U B L U B' L' R L' B' L u' l",
        "scrambleId": 4557412,
        "isExtra": 1,
        "groupId": "B"
      },
      {
        "scrambleNum": "2",
        "scramble": "B U' L' R U' R U B U B' R r' b",
        "scrambleId": 4557413,
        "isExtra": 1,
        "groupId": "B"
      },
      {
        "scrambleNum": "1",
        "scramble": "B' R' L' B L B' R' U L' B' R u l b'",
        "scrambleId": 4557414,
        "isExtra": 0,
        "groupId": "C"
      },
      {
        "scrambleNum": "2",
        "scramble": "U' R' B' U R' L' U' R B' U' B b'",
        "scrambleId": 4557415,
        "isExtra": 0,
        "groupId": "C"
      },
      {
        "scrambleNum": "3",
        "scramble": "B' R' U' R B' L U B R' L' R r'",
        "scrambleId": 4557416,
        "isExtra": 0,
        "groupId": "C"
      },
      {
        "scrambleNum": "4",
        "scramble": "R' L' B' U' R U R U' B' L U u",
        "scrambleId": 4557417,
        "isExtra": 0,
        "groupId": "C"
      },
      {
        "scrambleNum": "5",
        "scramble": "B L' U' R' U B L' U L' R B' u' b",
        "scrambleId": 4557418,
        "isExtra": 0,
        "groupId": "C"
      },
      {
        "scrambleNum": "1",
        "scramble": "B U B' R B' R' U R' B' R' L' u' r",
        "scrambleId": 4557419,
        "isExtra": 1,
        "groupId": "C"
      },
      {
        "scrambleNum": "2",
        "scramble": "L' U' L U' L' B L R' U' R' L r' b'",
        "scrambleId": 4557420,
        "isExtra": 1,
        "groupId": "C"
      }
    ],
    "f": [
      {
        "scrambleNum": "1",
        "scramble": "U' B R' L U B' L U B L' U l' r'",
        "scrambleId": 4557421,
        "isExtra": 0,
        "groupId": "A"
      },
      {
        "scrambleNum": "2",
        "scramble": "U R L B U B' R U' L' U' B' u' r'",
        "scrambleId": 4557422,
        "isExtra": 0,
        "groupId": "A"
      },
      {
        "scrambleNum": "3",
        "scramble": "L' R B' R B' U' L R U B' R",
        "scrambleId": 4557423,
        "isExtra": 0,
        "groupId": "A"
      },
      {
        "scrambleNum": "4",
        "scramble": "L' R B' L U' R B U' L R' B u' l' r' b",
        "scrambleId": 4557424,
        "isExtra": 0,
        "groupId": "A"
      },
      {
        "scrambleNum": "5",
        "scramble": "L' B U' B L R' L U B' R' L u l r",
        "scrambleId": 4557425,
        "isExtra": 0,
        "groupId": "A"
      },
      {
        "scrambleNum": "1",
        "scramble": "B' L R' U L' B' R B' L' U' B' u l' r b'",
        "scrambleId": 4557426,
        "isExtra": 1,
        "groupId": "A"
      },
      {
        "scrambleNum": "2",
        "scramble": "B R U R L' B R' L R L' U' u r' b",
        "scrambleId": 4557427,
        "isExtra": 1,
        "groupId": "A"
      },
      {
        "scrambleNum": "1",
        "scramble": "L R B' L' U' B U R' U B' R l r' b'",
        "scrambleId": 4557428,
        "isExtra": 0,
        "groupId": "B"
      },
      {
        "scrambleNum": "2",
        "scramble": "U' R' U' L U' L' R' U B U L' u' l",
        "scrambleId": 4557429,
        "isExtra": 0,
        "groupId": "B"
      },
      {
        "scrambleNum": "3",
        "scramble": "U' R L' B U B' R U L U' L u' l' r",
        "scrambleId": 4557430,
        "isExtra": 0,
        "groupId": "B"
      },
      {
        "scrambleNum": "4",
        "scramble": "U' B' U B' L R' U R' L' R' B l' r",
        "scrambleId": 4557431,
        "isExtra": 0,
        "groupId": "B"
      },
      {
        "scrambleNum": "5",
        "scramble": "R' U B L' R L' U' R' L' R' L u' l b'",
        "scrambleId": 4557432,
        "isExtra": 0,
        "groupId": "B"
      },
      {
        "scrambleNum": "1",
        "scramble": "L' U R' L U R L U B' U' R l' r' b",
        "scrambleId": 4557433,
        "isExtra": 1,
        "groupId": "B"
      },
      {
        "scrambleNum": "2",
        "scramble": "U R U' B L' R' U B L' B L r' b",
        "scrambleId": 4557434,
        "isExtra": 1,
        "groupId": "B"
      }
    ]
  }
}