{
  "eventId": "333",
  "competitionId": "StockholmsliganMamba2025",
  "rounds": {
    "f": [
      {
        "scrambleNum": "1",
        "scramble": "U2 L2 U' R2 U B2 F2 L2 B2 D' F L' F R' D2 B' D R2 B U",
        "scrambleId": "5142635",
        "isExtra": 0,
        "groupId": "A"
      },
      {
        "scrambleNum": "2",
        "scramble": "D' R2 U' L2 R2 B2 D' L2 R2 D2 L' F' U2 L U' B' L D2 U",
        "scrambleId": "5142636",
        "isExtra": 0,
        "groupId": "A"
      },
      {
        "scrambleNum": "3",
        "scramble": "B R2 D2 L2 D2 F2 L' R2 D2 L' U' B L2 R B L D2 F D2",
        "scrambleId": "5142637",
        "isExtra": 0,
        "groupId": "A"
      },
      {
        "scrambleNum": "4",
        "scramble": "R B L D2 F B' U2 L2 U' F2 R' F2 U2 R' D2 R' B2 R U",
        "scrambleId": "5142638",
        "isExtra": 0,
        "groupId": "A"
      },
      {
        "scrambleNum": "5",
        "scramble": "D R' B2 D2 F2 R' F2 R' U' B' R U' F2 U2 B D' U L2",
        "scrambleId": "5142639",
        "isExtra": 0,
        "groupId": "A"
      },
      {
        "scrambleNum": "1",
        "scramble": "L2 U' F2 D L2 D U F2 U F' L' B2 U2 F D' B' F' U B2 L",
        "scrambleId": "5142640",
        "isExtra": 1,
        "groupId": "A"
      },
      {
        "scrambleNum": "2",
        "scramble": "D2 L2 B2 D2 L' R2 F2 U2 F' R' D' B2 L2 D L' R' F' U' L2",
        "scrambleId": "5142641",
        "isExtra": 1,
        "groupId": "A"
      },
      {
        "scrambleNum": "1",
        "scramble": "U F' R2 B2 U2 L2 D B2 D' R2 D B F R D' L D2 U R2",
        "scrambleId": "5142642",
        "isExtra": 0,
        "groupId": "B"
      },
      {
        "scrambleNum": "2",
        "scramble": "B2 U2 R' B2 D2 L2 B2 R F2 R D L B U' L R F U R2 D",
        "scrambleId": "5142643",
        "isExtra": 0,
        "groupId": "B"
      },
      {
        "scrambleNum": "3",
        "scramble": "R D2 F U2 R F2 R2 B2 L B2 F' U' F' D' L U' F2 L",
        "scrambleId": "5142644",
        "isExtra": 0,
        "groupId": "B"
      },
      {
        "scrambleNum": "4",
        "scramble": "U2 L' D' L2 B2 U' F2 R' B' D B R' B L' D L2",
        "scrambleId": "5142645",
        "isExtra": 0,
        "groupId": "B"
      },
      {
        "scrambleNum": "5",
        "scramble": "D' L2 D' L2 U' L2 D2 F2 R2 L F2 D2 U' R2 U B D' U' B",
        "scrambleId": "5142646",
        "isExtra": 0,
        "groupId": "B"
      },
      {
        "scrambleNum": "1",
        "scramble": "D' L2 R' D2 B2 L' D2 F2 U2 L2 B R' D' F' D U L2 D L U2",
        "scrambleId": "5142647",
        "isExtra": 1,
        "groupId": "B"
      },
      {
        "scrambleNum": "2",
        "scramble": "U' D' F2 B2 R2 L B' D2 R U F2 B2 U2 R2 F2 B2 D' B2 R",
        "scrambleId": "5142648",
        "isExtra": 1,
        "groupId": "B"
      }
    ]
  }
}