{
  "eventId": "333bf",
  "competitionId": "SanRamonFall2025",
  "rounds": {
    "f": [
      {
        "scrambleNum": "1",
        "scramble": "U L' F2 R2 D2 L R2 B2 F2 U' F' D2 R' D F2 L B2 R2 B Rw2 Uw",
        "scrambleId": 5040560,
        "isExtra": 0,
        "groupId": "A"
      },
      {
        "scrambleNum": "2",
        "scramble": "U2 F2 L2 F' D2 B2 F R2 U2 L2 U' L' U F D F2 D F2 R2 Fw' Uw2",
        "scrambleId": 5040561,
        "isExtra": 0,
        "groupId": "A"
      },
      {
        "scrambleNum": "3",
        "scramble": "B L D2 B' R2 B R' D' L B' D2 R' F2 R' U2 L' B2 R' Fw' Uw2",
        "scrambleId": 5040562,
        "isExtra": 0,
        "groupId": "A"
      },
      {
        "scrambleNum": "1",
        "scramble": "D2 L D2 L D2 R D2 R F2 U' L U2 B' D' F L' F2 U B' F' Uw",
        "scrambleId": 5040563,
        "isExtra": 1,
        "groupId": "A"
      },
      {
        "scrambleNum": "2",
        "scramble": "L' U2 D' R2 L B2 D2 L' B L2 F R B2 L U2 F2 R' U2 Fw' Uw2",
        "scrambleId": 5040564,
        "isExtra": 1,
        "groupId": "A"
      },
      {
        "scrambleNum": "1",
        "scramble": "B2 U' L2 D U F2 L2 R2 B D' R' D2 F R D' F2 R' B D2 Rw'",
        "scrambleId": 5040565,
        "isExtra": 0,
        "groupId": "B"
      },
      {
        "scrambleNum": "2",
        "scramble": "D2 L' R' U2 B2 L' D2 F2 R2 F' D' F' L B2 D' R F U' L' D2 Rw2 Uw",
        "scrambleId": 5040566,
        "isExtra": 0,
        "groupId": "B"
      },
      {
        "scrambleNum": "3",
        "scramble": "R L' U' F2 B2 D' R2 U L2 B D2 B L2 F2 L2 B U2 R' U Rw Uw'",
        "scrambleId": 5040567,
        "isExtra": 0,
        "groupId": "B"
      },
      {
        "scrambleNum": "1",
        "scramble": "U2 F2 U2 R B2 L F2 L U2 L B' L F L2 F D2 U' F R' D2 Rw Uw2",
        "scrambleId": 5040568,
        "isExtra": 1,
        "groupId": "B"
      },
      {
        "scrambleNum": "2",
        "scramble": "F2 D L' U2 F2 D' B' R2 F' U B' R L F2 R U2 F2 R F2 Rw2 Uw2",
        "scrambleId": 5040569,
        "isExtra": 1,
        "groupId": "B"
      }
    ]
  }
}