{
  "eventId": "pyram",
  "competitionId": "OhioStateNearlyNewYears2024",
  "rounds": {
    "1": [
      {
        "scrambleNum": "1",
        "scramble": "B L R' U B' R U' B R L' B' l' r",
        "scrambleId": "4387434",
        "isExtra": 0,
        "groupId": "A"
      },
      {
        "scrambleNum": "2",
        "scramble": "U' L' B U' L' U' B' R' L R' L' u l' r",
        "scrambleId": "4387435",
        "isExtra": 0,
        "groupId": "A"
      },
      {
        "scrambleNum": "3",
        "scramble": "R L B U' R' L U R' L' U' R l",
        "scrambleId": "4387436",
        "isExtra": 0,
        "groupId": "A"
      },
      {
        "scrambleNum": "4",
        "scramble": "L' B L' R' B' R' U' B' R L B r b'",
        "scrambleId": "4387437",
        "isExtra": 0,
        "groupId": "A"
      },
      {
        "scrambleNum": "5",
        "scramble": "U' R U R' U' L' U B' U' B R u r' b",
        "scrambleId": "4387438",
        "isExtra": 0,
        "groupId": "A"
      },
      {
        "scrambleNum": "1",
        "scramble": "L U B L' R' U' B' U L' B' R r' b'",
        "scrambleId": "4387439",
        "isExtra": 1,
        "groupId": "A"
      },
      {
        "scrambleNum": "2",
        "scramble": "R' U' R' U' R L' U' R' L' U' B r' b'",
        "scrambleId": "4387440",
        "isExtra": 1,
        "groupId": "A"
      },
      {
        "scrambleNum": "1",
        "scramble": "B' R U L R' U' L' R L' U L' u l",
        "scrambleId": "4387441",
        "isExtra": 0,
        "groupId": "B"
      },
      {
        "scrambleNum": "2",
        "scramble": "L' B L' U B R B' U' B' R' U' u' l' r' b",
        "scrambleId": "4387442",
        "isExtra": 0,
        "groupId": "B"
      },
      {
        "scrambleNum": "3",
        "scramble": "L' B' R' L B R U R' L' B' R' u' l r b",
        "scrambleId": "4387443",
        "isExtra": 0,
        "groupId": "B"
      },
      {
        "scrambleNum": "4",
        "scramble": "R' L R U' B' R L' B U B R' u b",
        "scrambleId": "4387444",
        "isExtra": 0,
        "groupId": "B"
      },
      {
        "scrambleNum": "5",
        "scramble": "B L' R' B U' L' R U L' U' R",
        "scrambleId": "4387445",
        "isExtra": 0,
        "groupId": "B"
      },
      {
        "scrambleNum": "1",
        "scramble": "R U B L U' B' R' L' U L' R",
        "scrambleId": "4387446",
        "isExtra": 1,
        "groupId": "B"
      },
      {
        "scrambleNum": "2",
        "scramble": "U' L B R U' L B R' L' U L u r'",
        "scrambleId": "4387447",
        "isExtra": 1,
        "groupId": "B"
      },
      {
        "scrambleNum": "1",
        "scramble": "R' L B L' B R L R B U' B u' r'",
        "scrambleId": "4387448",
        "isExtra": 0,
        "groupId": "C"
      },
      {
        "scrambleNum": "2",
        "scramble": "L B' R U' B L B' L U L' U r b'",
        "scrambleId": "4387449",
        "isExtra": 0,
        "groupId": "C"
      },
      {
        "scrambleNum": "3",
        "scramble": "B' R B U R' L R' U L' R' L' b",
        "scrambleId": "4387450",
        "isExtra": 0,
        "groupId": "C"
      },
      {
        "scrambleNum": "4",
        "scramble": "U' B' R' L' U' B' R U L U L r b",
        "scrambleId": "4387451",
        "isExtra": 0,
        "groupId": "C"
      },
      {
        "scrambleNum": "5",
        "scramble": "L B' U' R' L' B R' L' U B R u' l' r' b'",
        "scrambleId": "4387452",
        "isExtra": 0,
        "groupId": "C"
      },
      {
        "scrambleNum": "1",
        "scramble": "L U R' U B' L' B L' U B' R' l'",
        "scrambleId": "4387453",
        "isExtra": 1,
        "groupId": "C"
      },
      {
        "scrambleNum": "2",
        "scramble": "L R B L' R' U R B' L' R' B' u' l b",
        "scrambleId": "4387454",
        "isExtra": 1,
        "groupId": "C"
      },
      {
        "scrambleNum": "1",
        "scramble": "B L B' U' B R' U B L' R' L' r b'",
        "scrambleId": "4387455",
        "isExtra": 0,
        "groupId": "D"
      },
      {
        "scrambleNum": "2",
        "scramble": "B' R' L R' L R U' L' U' R' L u' r b",
        "scrambleId": "4387456",
        "isExtra": 0,
        "groupId": "D"
      },
      {
        "scrambleNum": "3",
        "scramble": "L' B L B L R L R' U L' U' u l' r b",
        "scrambleId": "4387457",
        "isExtra": 0,
        "groupId": "D"
      },
      {
        "scrambleNum": "4",
        "scramble": "U' B U' L' R' L' U B' U' B' R u' l' r' b'",
        "scrambleId": "4387458",
        "isExtra": 0,
        "groupId": "D"
      },
      {
        "scrambleNum": "5",
        "scramble": "U' R U R' L' B L' R U' B U' l b'",
        "scrambleId": "4387459",
        "isExtra": 0,
        "groupId": "D"
      },
      {
        "scrambleNum": "1",
        "scramble": "R' L' U' R B R U' B' U R' L u l r' b'",
        "scrambleId": "4387460",
        "isExtra": 1,
        "groupId": "D"
      },
      {
        "scrambleNum": "2",
        "scramble": "L R' L' U' L' U B' L' B R L' r",
        "scrambleId": "4387461",
        "isExtra": 1,
        "groupId": "D"
      }
    ],
    "f": [
      {
        "scrambleNum": "1",
        "scramble": "R' B' L U R L' B' R B' R' L l' b'",
        "scrambleId": "4387462",
        "isExtra": 0,
        "groupId": "A"
      },
      {
        "scrambleNum": "2",
        "scramble": "U' R B L R L' R' L' B' U' B r b",
        "scrambleId": "4387463",
        "isExtra": 0,
        "groupId": "A"
      },
      {
        "scrambleNum": "3",
        "scramble": "L' B' R' L R B' U' L R U' B l' r b'",
        "scrambleId": "4387464",
        "isExtra": 0,
        "groupId": "A"
      },
      {
        "scrambleNum": "4",
        "scramble": "B' L' R B' U R' B' L' U B L' l b",
        "scrambleId": "4387465",
        "isExtra": 0,
        "groupId": "A"
      },
      {
        "scrambleNum": "5",
        "scramble": "B' U' L U B' U' B' L' R L' U u l' r",
        "scrambleId": "4387466",
        "isExtra": 0,
        "groupId": "A"
      },
      {
        "scrambleNum": "1",
        "scramble": "L U L R' L' U B' U' B U L' u b",
        "scrambleId": "4387467",
        "isExtra": 1,
        "groupId": "A"
      },
      {
        "scrambleNum": "2",
        "scramble": "L U L B' L' B L R' B' L' U u l r b'",
        "scrambleId": "4387468",
        "isExtra": 1,
        "groupId": "A"
      },
      {
        "scrambleNum": "1",
        "scramble": "L' R' L' U' B L U' B' L' U' B u r b'",
        "scrambleId": "4387469",
        "isExtra": 0,
        "groupId": "B"
      },
      {
        "scrambleNum": "2",
        "scramble": "B R' L B R' L' R' U R' L' U' u' l' r",
        "scrambleId": "4387470",
        "isExtra": 0,
        "groupId": "B"
      },
      {
        "scrambleNum": "3",
        "scramble": "L B' L R B' R' L U R' L' R u r",
        "scrambleId": "4387471",
        "isExtra": 0,
        "groupId": "B"
      },
      {
        "scrambleNum": "4",
        "scramble": "L U L' U R L' R B' R' U' B' u l' r",
        "scrambleId": "4387472",
        "isExtra": 0,
        "groupId": "B"
      },
      {
        "scrambleNum": "5",
        "scramble": "B' U' L' B' L B' U' B L' B L' u l",
        "scrambleId": "4387473",
        "isExtra": 0,
        "groupId": "B"
      },
      {
        "scrambleNum": "1",
        "scramble": "B' L' B' L R U' L' U' R B' U u l b'",
        "scrambleId": "4387474",
        "isExtra": 1,
        "groupId": "B"
      },
      {
        "scrambleNum": "2",
        "scramble": "L U R L B U' R' U R' L' B u l r",
        "scrambleId": "4387475",
        "isExtra": 1,
        "groupId": "B"
      }
    ]
  }
}